estrato.py
estrato-0.1.1.dist-info/DESCRIPTION.rst
estrato-0.1.1.dist-info/METADATA
estrato-0.1.1.dist-info/RECORD
estrato-0.1.1.dist-info/WHEEL
estrato-0.1.1.dist-info/entry_points.txt
estrato-0.1.1.dist-info/metadata.json
estrato-0.1.1.dist-info/top_level.txt
