Metadata-Version: 2.0
Name: estrato
Version: 0.1.1
Summary: Interact with an Electrum / Stratum server.
Home-page: https://github.com/iamale/estrato
Author: Ale
Author-email: hi@ale.rocks
License: UNKNOWN
Platform: UNKNOWN
Requires-Dist: prompt-toolkit (==1.0.8)
Requires-Dist: connectrum (==0.5.0)
